CHANGELOG.md
dj/__init__.py
dj/__main__.py
dj/auth/__init__.py
dj/auth/admin.py
dj/auth/apps.py
dj/auth/conf.py
dj/auth/forms.py
dj/auth/hashers.py
dj/auth/middleware.py
dj/auth/migrations/0001_initial.py
dj/auth/migrations/0002_session_data.py
dj/auth/migrations/0003_session_expire_date.py
dj/auth/migrations/0004_session_ip.py
dj/auth/migrations/0005_user_status.py
dj/auth/migrations/__init__.py
dj/auth/models.py
dj/auth/settings.py
dj/auth/templates/auth/login.html
dj/auth/templates/auth/logout.html
dj/auth/templates/auth/signup.html
dj/auth/urls.py
dj/auth/utils.py
dj/auth/validators/__init__.py
dj/auth/validators/password.py
dj/auth/validators/username.py
dj/auth/views.py
dj/blog/__init__.py
dj/blog/admin.py
dj/blog/apps.py
dj/blog/managers.py
dj/blog/migrations/0001_initial.py
dj/blog/migrations/0002_category_post_category_and_more.py
dj/blog/migrations/__init__.py
dj/blog/models.py
dj/blog/templates/blog/index.html
dj/blog/templates/blog/post.html
dj/blog/urls.py
dj/blog/views.py
dj/dj.toml
dj/project/__init__.py
dj/project/asgi.py
dj/project/settings/__init__.py
dj/project/settings/base.py
dj/project/settings/dev.py
dj/project/settings/prod.py
dj/project/settings/test.py
dj/project/static/css/styles.css
dj/project/static/js/scripts.js
dj/project/templates/base.html
dj/project/templates/index.html
dj/project/urls.py
dj/project/wsgi.py
dj/project_template/.gitignore
dj/project_template/manage.py
dj/project_template/project_name/__init__.py
dj/project_template/project_name/asgi.py
dj/project_template/project_name/settings/__init__.py
dj/project_template/project_name/settings/base.py
dj/project_template/project_name/settings/dev.py
dj/project_template/project_name/settings/local.py
dj/project_template/project_name/settings/prod.py
dj/project_template/project_name/settings/test.py
dj/project_template/project_name/urls.py
dj/project_template/project_name/views.py
dj/project_template/project_name/wsgi.py
dj/project_template/requirements/base.txt
djplus-3.0.0.dist-info/entry_points.txt
djplus-3.0.0.dist-info/LICENSE
djplus-3.0.0.dist-info/METADATA
djplus-3.0.0.dist-info/WHEEL
djplus-3.0.0.dist-info/RECORD
